pymatgen/io/aims/__init__.py
pymatgen/io/aims/inputs.py
pymatgen/io/aims/outputs.py
pymatgen/io/aims/sets/__init__.py
pymatgen/io/aims/sets/base.py
pymatgen/io/aims/sets/bs.py
pymatgen/io/aims/sets/core.py
pymatgen/io/aims/sets/magnetism.py
pymatgen_io_aims-0.0.5.dist-info/licenses/LICENSE
tests/io/aims/__init__.py
tests/io/aims/conftest.py
tests/io/aims/test_inputs.py
tests/io/aims/test_outputs.py
tests/io/aims/sets/__init__.py
tests/io/aims/sets/test_bs_generator.py
tests/io/aims/sets/test_gw_generator.py
tests/io/aims/sets/test_input_set.py
tests/io/aims/sets/test_md_generator.py
tests/io/aims/sets/test_relax_generator.py
tests/io/aims/sets/test_static_generator.py
tests/io/aims/sets/test_static_restart_from_relax_generator.py
pymatgen_io_aims-0.0.5.dist-info/METADATA
pymatgen_io_aims-0.0.5.dist-info/WHEEL
pymatgen_io_aims-0.0.5.dist-info/top_level.txt
pymatgen_io_aims-0.0.5.dist-info/RECORD
