Metadata-Version: 2.4
Name: pymatgen-io-aims
Version: 0.0.5
Summary: pymatgen-io-aims is a pymatgen addon that bridges the gap between FHI-aims and the pymatgen ecosystem
Author-email: Thomas Purcell <purcell@fhi-berlin.mpg.de>, Andrei Sobolev <sobolev@ms1p.org>
Maintainer-email: Thomas Purcell <purcell@fhi-berlin.mpg.de>, Andrei Sobolev <sobolev@ms1p.org>
Project-URL: Homepage, https://gitlab.com/FHI-aims-club/pymatgen-io-aims.git
Project-URL: Issues, https://gitlab.com/FHI-aims-club/pymatgen-io-aims/issues
Classifier: Programming Language :: Python :: 3
Classifier: Programming Language :: Python :: 3.10
Classifier: Programming Language :: Python :: 3.11
Classifier: Programming Language :: Python :: 3.12
Classifier: Development Status :: 2 - Pre-Alpha
Classifier: Intended Audience :: Science/Research
Classifier: License :: OSI Approved :: MIT License
Classifier: Operating System :: OS Independent
Classifier: Topic :: Scientific/Engineering :: Physics
Classifier: Topic :: Scientific/Engineering :: Chemistry
Requires-Python: <3.13,>=3.10
License-File: LICENSE
Requires-Dist: pymatgen>=2022.0.3
Requires-Dist: pyfhiaims>=0.0.9
Provides-Extra: dev
Requires-Dist: ruff; extra == "dev"
Requires-Dist: pytest; extra == "dev"
Requires-Dist: pytest_parametrize_cases; extra == "dev"
Requires-Dist: pre-commit; extra == "dev"
Dynamic: license-file
